upt_freebsd/__init__.py
upt_freebsd/upt_freebsd.py
upt_freebsd/templates/base.mk
upt_freebsd/templates/cran.mk
upt_freebsd/templates/perl.mk
upt_freebsd/templates/pkg-descr
upt_freebsd/templates/python.mk
upt_freebsd/templates/ruby.mk
upt_freebsd/tests/__init__.py
upt_freebsd/tests/test_cran_package.py
upt_freebsd/tests/test_freebsd_backend.py
upt_freebsd/tests/test_freebsd_package.py
upt_freebsd/tests/test_perl_package.py
upt_freebsd/tests/test_python_package.py
upt_freebsd/tests/test_ruby_package.py
upt_freebsd-0.3.dist-info/LICENSE
upt_freebsd-0.3.dist-info/METADATA
upt_freebsd-0.3.dist-info/WHEEL
upt_freebsd-0.3.dist-info/entry_points.txt
upt_freebsd-0.3.dist-info/top_level.txt
upt_freebsd-0.3.dist-info/RECORD
